rdhonest/__init__.py
rdhonest/cbound.py
rdhonest/cvb.py
rdhonest/datasets.py
rdhonest/kernels.py
rdhonest/npr.py
rdhonest/plots.py
rdhonest/py.typed
rdhonest/rd_bme.py
rdhonest/rd_opt.py
rdhonest/rdhonest.py
rdhonest/utils.py
rdhonest/variance.py
rdhonest/data/cghs.csv
rdhonest/data/headst.csv
rdhonest/data/lee08.csv
rdhonest/data/rcp.csv
rdhonest/data/rebp.csv
rdhonest-0.0.1.dist-info/METADATA
rdhonest-0.0.1.dist-info/WHEEL
rdhonest-0.0.1.dist-info/top_level.txt
rdhonest-0.0.1.dist-info/RECORD
