Metadata-Version: 2.4
Name: rdhonest
Version: 0.0.1
Summary: Honest inference in regression discontinuity designs
Author: Timothy B. Armstrong
Author-email: Michal Kolesar <kolesarmi@googlemail.com>
Maintainer-email: Michal Kolesar <kolesarmi@googlemail.com>
License: GPL-3.0
Project-URL: Homepage, https://github.com/kolesarm/RDHonest-py
Project-URL: Documentation, https://github.com/kolesarm/RDHonest-py#readme
Project-URL: Repository, https://github.com/kolesarm/RDHonest-py
Project-URL: Issues, https://github.com/kolesarm/RDHonest-py/issues
Project-URL: Changelog, https://github.com/kolesarm/RDHonest-py/blob/main/CHANGELOG.md
Project-URL: R Package, https://github.com/kolesarm/RDHonest
Keywords: regression discontinuity,RD design,causal inference,econometrics,nonparametric regression,confidence intervals,bias-aware inference,local polynomial regression,treatment effects
Classifier: Development Status :: 4 - Beta
Classifier: Intended Audience :: Science/Research
Classifier: Intended Audience :: Education
Classifier: License :: OSI Approved :: GNU General Public License v3 (GPLv3)
Classifier: Operating System :: OS Independent
Classifier: Programming Language :: Python :: 3
Classifier: Programming Language :: Python :: 3.8
Classifier: Programming Language :: Python :: 3.9
Classifier: Programming Language :: Python :: 3.10
Classifier: Programming Language :: Python :: 3.11
Classifier: Programming Language :: Python :: 3.12
Classifier: Programming Language :: Python :: 3.13
Classifier: Topic :: Scientific/Engineering
Classifier: Topic :: Scientific/Engineering :: Mathematics
Classifier: Topic :: Scientific/Engineering :: Information Analysis
Classifier: Typing :: Typed
Requires-Python: >=3.8
Requires-Dist: numpy>=1.20.0
Requires-Dist: scipy>=1.7.0
Requires-Dist: pandas>=1.3.0
Provides-Extra: plotting
Requires-Dist: matplotlib>=3.4.0; extra == "plotting"
Provides-Extra: dev
Requires-Dist: pytest>=7.0.0; extra == "dev"
Requires-Dist: pytest-cov>=4.0.0; extra == "dev"
Requires-Dist: matplotlib>=3.4.0; extra == "dev"
Requires-Dist: black>=23.0.0; extra == "dev"
Requires-Dist: isort>=5.12.0; extra == "dev"
Requires-Dist: mypy>=1.0.0; extra == "dev"
Requires-Dist: ruff>=0.1.0; extra == "dev"
Provides-Extra: docs
Requires-Dist: sphinx>=6.0.0; extra == "docs"
Requires-Dist: sphinx-rtd-theme>=1.2.0; extra == "docs"
Requires-Dist: numpydoc>=1.5.0; extra == "docs"
Provides-Extra: all
Requires-Dist: rdhonest[dev,docs,plotting]; extra == "all"
